onnion/__init__.py
onnion/main.py
onnion-0.8.1.dist-info/entry_points.txt
onnion-0.8.1.dist-info/LICENSE
onnion-0.8.1.dist-info/WHEEL
onnion-0.8.1.dist-info/METADATA
onnion-0.8.1.dist-info/RECORD
